composed_configuration/__init__.py
composed_configuration/_allauth.py
composed_configuration/_base.py
composed_configuration/_celery.py
composed_configuration/_configuration.py
composed_configuration/_cors.py
composed_configuration/_database.py
composed_configuration/_debug.py
composed_configuration/_django.py
composed_configuration/_docker.py
composed_configuration/_email.py
composed_configuration/_extensions.py
composed_configuration/_filter.py
composed_configuration/_girder_utils.py
composed_configuration/_https.py
composed_configuration/_logging.py
composed_configuration/_rest_framework.py
composed_configuration/_sentry.py
composed_configuration/_static.py
composed_configuration/_storage.py
composed_configuration/_values.py
composed_configuration/_allauth_support/__init__.py
composed_configuration/_allauth_support/adapter.py
composed_configuration/_allauth_support/apps.py
composed_configuration/_allauth_support/createsuperuser.py
composed_configuration/_allauth_support/receiver.py
composed_configuration/_allauth_support/utils.py
composed_configuration/_allauth_support/management/commands/createsuperuser.py
composed_configuration/sentry/__init__.py
composed_configuration/sentry/apps.py
django_composed_configuration-0.25.0.dist-info/METADATA
django_composed_configuration-0.25.0.dist-info/WHEEL
django_composed_configuration-0.25.0.dist-info/licenses/LICENSE
django_composed_configuration-0.25.0.dist-info/RECORD
